{
  "format_version": "1.0.0",
  "minecraft:recipe_shaped": {
    "description": {
      "identifier": "minecraft:repeater"
    },
    "tags": [
      "crafting_table"
    ],
    "pattern": [
      "TRT",
      "###"
    ],
    "key": {
      "#": [
        {
          "item": "minecraft:stone"
        }
      ],
      "T": [
        {
          "item": "minecraft:redstone_torch"
        }
      ],
      "R": [
        {
          "item": "minecraft:redstone"
        }
      ]
    },
    "result": {
      "item": "minecraft:repeater",
      "count": 1
    }
  }
}

